{
    "Green 700": "#265600",
    "Green 500": "#3F8500",
    "NVIDIA Green": "#76B900",
    "Green 100": "#BFF230",
    "Green 050": "#CFFF40",
    "Teal 700": "#04554B",
    "Teal 500": "#0D8473",
    "Teal 300": "#1DBBA4",
    "Teal 100": "#9AEEF5",
    "Teal 050": "#ADDCF8",
    "Blue 800": "#002781",
    "Blue 700": "#0046A4",
    "Blue 500": "#0740DF",
    "Blue 200": "#7CD7FE",
    "Blue 050": "#CBF5FF",
    "Purple 800": "#4D1368",
    "Purple 700": "#7419D9",
    "Purple 600": "#952F6C",
    "Purple 400": "#C359EF",
    "Purple 100": "#F9D4FF",
    "Fuchsia 800": "#5D1337",
    "Fuchsia 700": "#8C1555",
    "Fuchsia 500": "#D23082",
    "Fuchsia 300": "#FC79CA",
    "Fuchsia 100": "#FFD3F2",
    "Red 800": "#650B0B",
    "Red 700": "#951615",
    "Red 500": "#E52020",
    "Red 300": "#FF7181",
    "Red 100": "#FFD7D1",
    "Yellow 400": "#FD6500",
    "Yellow 300": "#EF9100",
    "Yellow 200": "#F9C500",
    "Yellow 100": "#FCED7B",
    "Yellow 050": "#FEEEED",
    "Gray 700": "#4B4B4B",
    "Gray 600": "#636363",
    "Gray 500": "#757575",
    "Gray 400": "#989898",
    "Gray 300": "#A7A7A7"
}